rq_runner/__init__.py
rq_runner/apps.py
rq_runner/executor.py
rq_runner/job.py
rq_runner/management/__init__.py
rq_runner/management/commands/__init__.py
rq_runner/management/commands/config.py
rq_runner/management/commands/enqueue.py
rq_runner/management/commands/worker.py
rq_runner/plugins/__init__.py
rq_runner/plugins/callbacks/__init__.py
rq_runner/plugins/callbacks/awx_display.py
rq_runner/settings.py
rq_runner/tests.py
rq_runner/utils.py
rq_runner-0.1.0.dist-info/WHEEL
rq_runner-0.1.0.dist-info/entry_points.txt
rq_runner-0.1.0.dist-info/METADATA
rq_runner-0.1.0.dist-info/RECORD
