Metadata-Version: 2.3
Name: rq-runner
Version: 0.1.0
Summary: RQ worker for django
Author: pyqf
Requires-Dist: ansible-core>=2.19.2,<2.20
Requires-Dist: ansible-runner>=2.4.1
Requires-Dist: django>=4.1.13
Requires-Dist: dynaconf>=3.2.11
Requires-Dist: rq>=2.6.0
Requires-Dist: rq-result
Requires-Python: >=3.11
